{
    "entries":  [
                    {
                        "name":  "Nordól",
                        "id":  4,
                        "guid":  53674121,
                        "type":  "Paladin",
                        "icon":  "Paladin-Holy",
                        "timestamp":  13613494,
                        "fight":  54,
                        "damage":  {
                                       "total":  10433,
                                       "activeTime":  0,
                                       "activeTimeReduced":  0,
                                       "overheal":  13048,
                                       "abilities":  [
                                                         {
                                                             "guid":  30619,
                                                             "name":  "Cleave",
                                                             "total":  10433,
                                                             "type":  1,
                                                             "icon":  "ability_warrior_cleave.jpg"
                                                         }
                                                     ],
                                       "damageAbilities":  [

                                                           ],
                                       "sources":  [
                                                       {
                                                           "name":  "Magtheridon",
                                                           "total":  10433,
                                                           "type":  "Boss"
                                                       }
                                                   ]
                                   },
                        "healing":  {
                                        "total":  0,
                                        "activeTime":  0,
                                        "activeTimeReduced":  0,
                                        "abilities":  [

                                                      ],
                                        "damageAbilities":  [

                                                            ],
                                        "sources":  [

                                                    ]
                                    },
                        "deathWindow":  0,
                        "overkill":  1626,
                        "events":  [
                                       {
                                           "timestamp":  13613484,
                                           "type":  "damage",
                                           "sourceID":  299,
                                           "sourceIsFriendly":  false,
                                           "targetID":  4,
                                           "targetIsFriendly":  true,
                                           "ability":  {
                                                           "name":  "Cleave",
                                                           "guid":  30619,
                                                           "type":  1,
                                                           "abilityIcon":  "ability_warrior_cleave.jpg"
                                                       },
                                           "fight":  54,
                                           "hitType":  1,
                                           "amount":  8807,
                                           "mitigated":  13048,
                                           "unmitigatedAmount":  23481,
                                           "overkill":  1626,
                                           "isAoE":  true
                                       }
                                   ],
                        "killingBlow":  {
                                            "name":  "Cleave",
                                            "guid":  30619,
                                            "type":  1,
                                            "abilityIcon":  "ability_warrior_cleave.jpg"
                                        }
                    },
                    {
                        "name":  "Panteleykin",
                        "id":  11,
                        "guid":  44919026,
                        "type":  "Warrior",
                        "icon":  "Warrior-Arms",
                        "timestamp":  13636308,
                        "fight":  54,
                        "damage":  {
                                       "total":  13706,
                                       "activeTime":  0,
                                       "activeTimeReduced":  0,
                                       "overheal":  780,
                                       "abilities":  [
                                                         {
                                                             "guid":  36449,
                                                             "name":  "Debris",
                                                             "total":  6886,
                                                             "type":  1,
                                                             "icon":  "spell_nature_earthquake.jpg"
                                                         },
                                                         {
                                                             "guid":  30410,
                                                             "name":  "Shadow Grasp",
                                                             "total":  6820,
                                                             "type":  32,
                                                             "icon":  "spell_shadow_unsummonbuilding.jpg"
                                                         }
                                                     ],
                                       "damageAbilities":  [

                                                           ],
                                       "sources":  [
                                                       {
                                                           "name":  "Environment",
                                                           "total":  13706,
                                                           "type":  "Boss"
                                                       }
                                                   ]
                                   },
                        "healing":  {
                                        "total":  2496,
                                        "activeTime":  0,
                                        "activeTimeReduced":  0,
                                        "abilities":  [
                                                          {
                                                              "guid":  27237,
                                                              "name":  "Master Healthstone",
                                                              "total":  2496,
                                                              "type":  1,
                                                              "icon":  "inv_stone_04.jpg"
                                                          }
                                                      ],
                                        "damageAbilities":  [
                                                                {
                                                                    "guid":  30410,
                                                                    "name":  "Shadow Grasp",
                                                                    "total":  2496,
                                                                    "type":  32,
                                                                    "icon":  "spell_shadow_unsummonbuilding.jpg"
                                                                }
                                                            ],
                                        "sources":  [
                                                        {
                                                            "name":  "Panteleykin",
                                                            "total":  2496,
                                                            "type":  "Warrior"
                                                        }
                                                    ]
                                    },
                        "deathWindow":  11262,
                        "overkill":  900,
                        "events":  [
                                       {
                                           "timestamp":  13636281,
                                           "type":  "damage",
                                           "source":  {
                                                          "name":  "Environment",
                                                          "id":  -1,
                                                          "guid":  0,
                                                          "type":  "Boss",
                                                          "icon":  "Boss"
                                                      },
                                           "sourceIsFriendly":  false,
                                           "targetID":  11,
                                           "targetIsFriendly":  true,
                                           "ability":  {
                                                           "name":  "Debris",
                                                           "guid":  36449,
                                                           "type":  1,
                                                           "abilityIcon":  "spell_nature_earthquake.jpg"
                                                       },
                                           "fight":  54,
                                           "hitType":  1,
                                           "amount":  5986,
                                           "unmitigatedAmount":  6260,
                                           "overkill":  900,
                                           "isAoE":  true
                                       },
                                       {
                                           "timestamp":  13633010,
                                           "type":  "damage",
                                           "source":  {
                                                          "name":  "Environment",
                                                          "id":  -1,
                                                          "guid":  0,
                                                          "type":  "Boss",
                                                          "icon":  "Boss"
                                                      },
                                           "sourceIsFriendly":  false,
                                           "targetID":  11,
                                           "targetIsFriendly":  true,
                                           "ability":  {
                                                           "name":  "Shadow Grasp",
                                                           "guid":  30410,
                                                           "type":  32,
                                                           "abilityIcon":  "spell_shadow_unsummonbuilding.jpg"
                                                       },
                                           "fight":  54,
                                           "hitType":  1,
                                           "amount":  880,
                                           "unmitigatedAmount":  800,
                                           "isAoE":  false,
                                           "tick":  true
                                       },
                                       {
                                           "timestamp":  13632004,
                                           "type":  "damage",
                                           "source":  {
                                                          "name":  "Environment",
                                                          "id":  -1,
                                                          "guid":  0,
                                                          "type":  "Boss",
                                                          "icon":  "Boss"
                                                      },
                                           "sourceIsFriendly":  false,
                                           "targetID":  11,
                                           "targetIsFriendly":  true,
                                           "ability":  {
                                                           "name":  "Shadow Grasp",
                                                           "guid":  30410,
                                                           "type":  32,
                                                           "abilityIcon":  "spell_shadow_unsummonbuilding.jpg"
                                                       },
                                           "fight":  54,
                                           "hitType":  16,
                                           "amount":  440,
                                           "mitigated":  360,
                                           "unmitigatedAmount":  800,
                                           "resisted":  400,
                                           "isAoE":  false,
                                           "tick":  true
                                       }
                                   ],
                        "killingBlow":  {
                                            "name":  "Debris",
                                            "guid":  36449,
                                            "type":  1,
                                            "abilityIcon":  "spell_nature_earthquake.jpg"
                                        }
                    },
                    {
                        "name":  "Dieselprime",
                        "id":  6,
                        "guid":  51757666,
                        "type":  "Mage",
                        "icon":  "Mage-Arcane",
                        "timestamp":  13636309,
                        "fight":  54,
                        "damage":  {
                                       "total":  10255,
                                       "activeTime":  0,
                                       "activeTimeReduced":  0,
                                       "overheal":  1677,
                                       "abilities":  [
                                                         {
                                                             "guid":  36449,
                                                             "name":  "Debris",
                                                             "total":  5954,
                                                             "type":  1,
                                                             "icon":  "spell_nature_earthquake.jpg"
                                                         },
                                                         {
                                                             "guid":  30757,
                                                             "name":  "Conflagration",
                                                             "total":  4301,
                                                             "type":  4,
                                                             "icon":  "spell_fire_incinerate.jpg"
                                                         }
                                                     ],
                                       "damageAbilities":  [

                                                           ],
                                       "sources":  [
                                                       {
                                                           "name":  "Environment",
                                                           "total":  5954,
                                                           "type":  "Boss"
                                                       },
                                                       {
                                                           "name":  "Past Self",
                                                           "total":  4301,
                                                           "type":  "NPC"
                                                       }
                                                   ]
                                   },
                        "healing":  {
                                        "total":  0,
                                        "activeTime":  0,
                                        "activeTimeReduced":  0,
                                        "abilities":  [

                                                      ],
                                        "damageAbilities":  [

                                                            ],
                                        "sources":  [

                                                    ]
                                    },
                        "deathWindow":  19628,
                        "overkill":  2252,
                        "events":  [
                                       {
                                           "timestamp":  13636282,
                                           "type":  "damage",
                                           "source":  {
                                                          "name":  "Environment",
                                                          "id":  -1,
                                                          "guid":  0,
                                                          "type":  "Boss",
                                                          "icon":  "Boss"
                                                      },
                                           "sourceIsFriendly":  false,
                                           "targetID":  6,
                                           "targetIsFriendly":  true,
                                           "ability":  {
                                                           "name":  "Debris",
                                                           "guid":  36449,
                                                           "type":  1,
                                                           "abilityIcon":  "spell_nature_earthquake.jpg"
                                                       },
                                           "fight":  54,
                                           "hitType":  1,
                                           "amount":  3702,
                                           "unmitigatedAmount":  5954,
                                           "overkill":  2252,
                                           "isAoE":  true
                                       },
                                       {
                                           "timestamp":  13623638,
                                           "type":  "damage",
                                           "source":  {
                                                          "name":  "Past Self",
                                                          "id":  307,
                                                          "guid":  181832,
                                                          "type":  "NPC",
                                                          "icon":  "custom-icon-spell_fire_incinerate.jpg"
                                                      },
                                           "sourceInstance":  1,
                                           "sourceIsFriendly":  false,
                                           "targetID":  6,
                                           "targetIsFriendly":  true,
                                           "ability":  {
                                                           "name":  "Conflagration",
                                                           "guid":  30757,
                                                           "type":  4,
                                                           "abilityIcon":  "spell_fire_incinerate.jpg"
                                                       },
                                           "fight":  54,
                                           "hitType":  1,
                                           "amount":  748,
                                           "unmitigatedAmount":  748,
                                           "isAoE":  true,
                                           "tick":  true
                                       },
                                       {
                                           "timestamp":  13622645,
                                           "type":  "damage",
                                           "source":  {
                                                          "name":  "Past Self",
                                                          "id":  307,
                                                          "guid":  181832,
                                                          "type":  "NPC",
                                                          "icon":  "custom-icon-spell_fire_incinerate.jpg"
                                                      },
                                           "sourceInstance":  1,
                                           "sourceIsFriendly":  false,
                                           "targetID":  6,
                                           "targetIsFriendly":  true,
                                           "ability":  {
                                                           "name":  "Conflagration",
                                                           "guid":  30757,
                                                           "type":  4,
                                                           "abilityIcon":  "spell_fire_incinerate.jpg"
                                                       },
                                           "fight":  54,
                                           "hitType":  16,
                                           "amount":  561,
                                           "mitigated":  186,
                                           "unmitigatedAmount":  747,
                                           "resisted":  187,
                                           "isAoE":  true,
                                           "tick":  true
                                       }
                                   ],
                        "killingBlow":  {
                                            "name":  "Debris",
                                            "guid":  36449,
                                            "type":  1,
                                            "abilityIcon":  "spell_nature_earthquake.jpg"
                                        }
                    },
                    {
                        "name":  "Gutsbulla",
                        "id":  15,
                        "guid":  51980592,
                        "type":  "Druid",
                        "icon":  "Druid-Feral",
                        "timestamp":  13654324,
                        "fight":  54,
                        "damage":  {
                                       "total":  12456,
                                       "activeTime":  0,
                                       "activeTimeReduced":  0,
                                       "overheal":  633,
                                       "abilities":  [
                                                         {
                                                             "guid":  36449,
                                                             "name":  "Debris",
                                                             "total":  6741,
                                                             "type":  1,
                                                             "icon":  "spell_nature_earthquake.jpg"
                                                         },
                                                         {
                                                             "guid":  30410,
                                                             "name":  "Shadow Grasp",
                                                             "total":  5305,
                                                             "type":  32,
                                                             "icon":  "spell_shadow_unsummonbuilding.jpg"
                                                         },
                                                         {
                                                             "guid":  13241,
                                                             "name":  "Goblin Sapper Charge",
                                                             "total":  410,
                                                             "type":  4,
                                                             "icon":  "spell_fire_selfdestruct.jpg"
                                                         }
                                                     ],
                                       "damageAbilities":  [

                                                           ],
                                       "sources":  [
                                                       {
                                                           "name":  "Environment",
                                                           "total":  12046,
                                                           "type":  "Boss"
                                                       },
                                                       {
                                                           "name":  "Gutsbulla",
                                                           "total":  410,
                                                           "type":  "Druid"
                                                       }
                                                   ]
                                   },
                        "healing":  {
                                        "total":  2118,
                                        "activeTime":  0,
                                        "activeTimeReduced":  0,
                                        "abilities":  [
                                                          {
                                                              "guid":  26980,
                                                              "name":  "Regrowth",
                                                              "total":  1714,
                                                              "type":  8,
                                                              "icon":  "spell_nature_resistnature.jpg"
                                                          },
                                                          {
                                                              "guid":  34299,
                                                              "name":  "Leader of the Pack",
                                                              "total":  404,
                                                              "type":  1,
                                                              "icon":  "spell_nature_unyeildingstamina.jpg"
                                                          }
                                                      ],
                                        "damageAbilities":  [
                                                                {
                                                                    "guid":  36449,
                                                                    "name":  "Debris",
                                                                    "total":  1748,
                                                                    "type":  1,
                                                                    "icon":  "spell_nature_earthquake.jpg"
                                                                },
                                                                {
                                                                    "guid":  30410,
                                                                    "name":  "Shadow Grasp",
                                                                    "total":  370,
                                                                    "type":  32,
                                                                    "icon":  "spell_shadow_unsummonbuilding.jpg"
                                                                }
                                                            ],
                                        "sources":  [
                                                        {
                                                            "name":  "Gutsbulla",
                                                            "total":  2118,
                                                            "type":  "Druid"
                                                        }
                                                    ]
                                    },
                        "deathWindow":  24519,
                        "overkill":  254,
                        "events":  [
                                       {
                                           "timestamp":  13654324,
                                           "type":  "damage",
                                           "source":  {
                                                          "name":  "Environment",
                                                          "id":  -1,
                                                          "guid":  0,
                                                          "type":  "Boss",
                                                          "icon":  "Boss"
                                                      },
                                           "sourceIsFriendly":  false,
                                           "targetID":  15,
                                           "targetIsFriendly":  true,
                                           "ability":  {
                                                           "name":  "Shadow Grasp",
                                                           "guid":  30410,
                                                           "type":  32,
                                                           "abilityIcon":  "spell_shadow_unsummonbuilding.jpg"
                                                       },
                                           "fight":  54,
                                           "hitType":  1,
                                           "amount":  594,
                                           "unmitigatedAmount":  848,
                                           "overkill":  254,
                                           "isAoE":  false,
                                           "tick":  true
                                       },
                                       {
                                           "timestamp":  13653316,
                                           "type":  "damage",
                                           "source":  {
                                                          "name":  "Environment",
                                                          "id":  -1,
                                                          "guid":  0,
                                                          "type":  "Boss",
                                                          "icon":  "Boss"
                                                      },
                                           "sourceIsFriendly":  false,
                                           "targetID":  15,
                                           "targetIsFriendly":  true,
                                           "ability":  {
                                                           "name":  "Shadow Grasp",
                                                           "guid":  30410,
                                                           "type":  32,
                                                           "abilityIcon":  "spell_shadow_unsummonbuilding.jpg"
                                                       },
                                           "fight":  54,
                                           "hitType":  1,
                                           "amount":  849,
                                           "unmitigatedAmount":  849,
                                           "isAoE":  false,
                                           "tick":  true
                                       },
                                       {
                                           "timestamp":  13652304,
                                           "type":  "damage",
                                           "source":  {
                                                          "name":  "Environment",
                                                          "id":  -1,
                                                          "guid":  0,
                                                          "type":  "Boss",
                                                          "icon":  "Boss"
                                                      },
                                           "sourceIsFriendly":  false,
                                           "targetID":  15,
                                           "targetIsFriendly":  true,
                                           "ability":  {
                                                           "name":  "Shadow Grasp",
                                                           "guid":  30410,
                                                           "type":  32,
                                                           "abilityIcon":  "spell_shadow_unsummonbuilding.jpg"
                                                       },
                                           "fight":  54,
                                           "hitType":  16,
                                           "amount":  637,
                                           "mitigated":  211,
                                           "unmitigatedAmount":  848,
                                           "resisted":  212,
                                           "isAoE":  false,
                                           "tick":  true
                                       }
                                   ],
                        "killingBlow":  {
                                            "name":  "Shadow Grasp",
                                            "guid":  30410,
                                            "type":  32,
                                            "abilityIcon":  "spell_shadow_unsummonbuilding.jpg"
                                        }
                    }
                ]
}